activitystream/__init__.py
activitystream/base.py
activitystream/managers.py
activitystream/storage/__init__.py
activitystream/storage/base.py
activitystream/storage/mingstorage.py
activitystream/storage/pymongostorage.py
activitystream-0.5.1.dist-info/licenses/LICENSE
activitystream-0.5.1.dist-info/METADATA
activitystream-0.5.1.dist-info/WHEEL
activitystream-0.5.1.dist-info/top_level.txt
activitystream-0.5.1.dist-info/RECORD
